aiocontroller/__about__.py
aiocontroller/__init__.py
aiocontroller/abstraction.py
aiocontroller/client.py
aiocontroller/endpoints.py
aiocontroller/exceptions.py
aiocontroller/server.py
aiocontroller-0.0.11.dist-info/METADATA
aiocontroller-0.0.11.dist-info/WHEEL
aiocontroller-0.0.11.dist-info/licenses/LICENSE.txt
aiocontroller-0.0.11.dist-info/RECORD
